Metadata-Version: 2.4
Name: adafruit-circuitpython-checkbox
Version: 1.0.0
Summary: A displayio based CheckBox widget. It includes a text label and a box that can be checked or unchecked.
Author-email: Adafruit Industries <circuitpython@adafruit.com>
License: MIT
Project-URL: Homepage, https://github.com/adafruit/Adafruit_CircuitPython_CheckBox
Keywords: adafruit,blinka,circuitpython,micropython,checkbox,checkbox,check,box,widget,GUI,UI,interface,toggle
Classifier: Intended Audience :: Developers
Classifier: Topic :: Software Development :: Libraries
Classifier: Topic :: Software Development :: Embedded Systems
Classifier: Topic :: System :: Hardware
Classifier: License :: OSI Approved :: MIT License
Classifier: Programming Language :: Python :: 3
License-File: LICENSE
Requires-Dist: Adafruit-Blinka
Requires-Dist: adafruit-circuitpython-anchored-group
Requires-Dist: adafruit-circuitpython-display-text
Provides-Extra: optional
Dynamic: license-file
